{
  "project_info": {
    "project_number": "841519919014",
    "project_id": "fir-demo-442cf",
    "storage_bucket": "fir-demo-442cf.appspot.com"
  },
  "client": [
    {
      "client_info": {
        "mobilesdk_app_id": "1:841519919014:android:afc41ae43040e85c03e967",
        "android_client_info": {
          "package_name": "com.example.firebasedemo"
        }
      },
      "oauth_client": [],
      "api_key": [
        {
          "current_key": "AIzaSyCMgkD9F_cg6NEn0oSkzrnjXO50p4l6NRA"
        }
      ],
      "services": {
        "appinvite_service": {
          "other_platform_oauth_client": []
        }
      }
    }
  ],
  "configuration_version": "1"
}